{"baseSetSize":1,"cards":[],"code":"PLNY","isFoilOnly":true,"isOnlineOnly":false,"keyruneCode":"PMEI","languages":["English"],"name":"Lunar New Year 2018","releaseDate":"2018-02-16","tokenSetCode":"PLNY","tokens":[{"artist":"YW Tang","artistIds":["63b2909b-7102-49c5-8f9d-6116a1913308"],"availability":["paper"],"borderColor":"black","colorIdentity":[],"colors":[],"finishes":["foil"],"frameVersion":"2015","hasFoil":true,"hasNonFoil":false,"identifiers":{"mtgjsonV4Id":"5c46c1f2-095e-54ee-8fde-bbc105d8731c","scryfallCardBackId":"2ce31f17-2418-4063-ba6f-87ec3220b534","scryfallId":"fa8bbe0c-3813-4e3f-9bcf-cffe4fed6341","scryfallIllustrationId":"94982a19-7c1d-4c90-a57d-51ae0cc3804a","scryfallOracleId":"3c549374-6c37-42e0-8d88-a8555d46732d","tcgplayerProductId":"165632"},"isPromo":true,"isReprint":true,"language":"English","layout":"token","name":"Treasure","number":"1","relatedCards":{"reverseRelated":["Academy Manufactor","An Offer You Can't Refuse","Ancestors' Aid","Ancient Copper Dragon","Atsushi, the Blazing Sky","Axgard Artisan","Baeloth Barrityl, Entertainer","Bank Job","Battle Angels of Tyr","Beamtown Beatstick","Big Score","Big Spender","Bilbo, Retired Burglar","Bill Ferny, Bree Swindler","Black Market Connections","Black Market Tycoon","Blood Money","Bonehoard Dracosaur","Boneyard Desecrator","Bootleggers' Stash","Bottle-Cap Blast","Boxing Ring","Brass's Bounty","Brazen Freebooter","Breeches, Eager Pillager","Bucknard's Everfull Purse","Burakos, Party Leader","Burdened Aerialist","Buy Your Silence","Captain Lannery Storm","Careening Mine Cart","Cavern-Hoard Dragon","Centrifuge","Charming Scoundrel","City of Death","Collector's Vault","Contested Game Ball","Contract Killing","Corsair Captain","Covetous Elegy","Crack Open","Creative Outburst","Culmination of Studies","Currency Converter","Cutthroat Negotiator","Deadeye Plunderers","Deadly Derision","Deadly Dispute","Decadent Dragon // Expensive Taste","Depths of Desire","Descent into Avernus","Diamond Pick-Axe","Dihada, Binder of Wills","Dire Fleet Hoarder","Discerning Financier","Dockside Extortionist","Don Andres, the Renegade","Done for the Day","Dungeon of the Mad Mage","Dungeoneer's Pack","Elemental Masterpiece","Emissary Green","Enterprising Scallywag","Erestor of the Council","Excavation Technique","Exhibition Magician","Exit Through the Grift Shop","Fable of the Mirror-Breaker // Reflection of Kiki-Jiki","Fae Offering","Fain, the Broker","Fake Your Own Death","Flick a Coin","Forging the Tyrite Sword","Forsworn Paladin","Furnace Reins","Gadrak, the Crown-Scourge","Gala Greeters","Galadriel, Gift-Giver","Galazeth Prismari","Ganax, Astral Hunter","Gemcutter Buccaneer","Generous Plunderer","Gilded Pinions","Gimli of the Glittering Caves","Gleaming Barrier","Glittermonger","Gluntch, the Bestower","Glóin, Dwarf Emissary","Goblin Airbrusher","Goblin Shaman","Gold Pan","Gold Rush","Goldspan Dragon","Goldvein Hydra","Goldvein Pick","Gorbag of Minas Morgul","Grabby Giant // That's Mine","Great Train Heist","Greedy Freebooter","Grim Bounty","Grim Hireling","Guild Artisan","Halo Scarab","Heap Gate","Heartless Pillage","Hell to Pay","Henry Wu, InGen Geneticist","Herald of Hadar","Hit the Mother Lode","Hoard Hauler","Hoard Robber","Hoarding Ogre","Hornswoggle","Hullbreacher","Ignacio of Myra's Marvels","Impetuous Lootmonger","Improvised Weaponry","Impulsive Pilferer","Indulge // Excess","Ingenious Mastery","Inspired Tinkering","Instrument of the Bards","Invasion of Ergamon // Truga Cliffcharger","Involuntary Employment","James, Wandering Dad // Follow Him","Jan Jansen, Chaos Crafter","Jared Carthalion","Jewel Thief","Jewel-Eyed Cobra","Jolene, Plundering Pugilist","Jolene, the Plunder Queen","Kalain, Reclusive Painter","Kamachal, Ship's Mascot","Kellogg, Dangerous Mind","Kerblam! Warehouse","Korvold and the Noble Thief","Lara Croft, Tomb Raider","Life Insurance","Lobelia Sackville-Baggins","Loot Dispute","Lost Mine of Phandelver","Lotho, Corrupt Shirriff","Luck Bobblehead","Luxurious Locomotive","Magda, Brazen Outlaw","Magda, the Hoardmaster","Magma Opus","Magmatic Galleon","Mahadi, Emporium Master","Malcolm, Keen-Eyed Navigator","Malik, Grim Manipulator","Marching Duodrone","Mari, the Killing Quill","Marut","Master of Ceremonies","Mastermind Plum","Meet and Greet \"Sisay\"","Megaton's Fate","Mine Raider","Mines of Moria","Misfortune Teller","Monologue Tax","Most Wanted","Mr. House, President and CEO","New New York","Noble's Purse","North Pole Research Base","Nuka-Cola Vending Machine","Oath of the Grey Host","Ognis, the Dragon's Lash","Old Gnawbone","Old Rutstein","Olivia, Opulent Outlaw","Pain Distributor","Patient Naturalist","Patron of the Arts","Pick-a-Beeble","Pinkie Pie","Pirate's Pillage","Pirate's Prize","Pitiless Plunderer","Plundering Barbarian","Plundering Pirate","Poetic Ingenuity","Prismari Command","Prized Statue","Prizefight","Professional Face-Breaker","Prosper, Tome-Bound","Prosperous Innkeeper","Prosperous Partnership","Prosperous Pirates","Prosperous Thief","Prying Blade","RMS Titanic","Racketeer Boss","Ragavan, Nimble Pilferer","Rain of Riches","Ramirez DePietro, Pillager","Rankle and Torbran","Rapacious Dragon","Rashmi and Ragavan","Reckless Endeavor","Reckless Lackey","Reckoner Bankbuster","Redcap Thief","Redrock Sentinel","Revel in Riches","Riveteers Requisitioner","Rose Room Treasurer","Ruthless Knave","Ruthless Technomancer","Safana, Calimport Cutthroat","Sailor of Means","Scion of Opulence","Seize the Spoils","Seize the Spotlight","Shambling Ghast","Shiny Impetus","Skullport Merchant","Smashing Success","Smaug","Smoke Blessing","Smoke Spirits' Aid","Smothering Tithe","Smuggler's Share","Song of Eärendil","Spectrox Mines","Spell Swindle","Spiked Pit Trap","Spiteful Banditry","Spiteful Repossession","Sticky Fingers","Stimulus Package","Storm the Vault // Vault of Catlacan","Storm-Kiln Artist","Strike It Rich","Sudden Breakthrough","Surly Badgersaur","Swarming of Moria","Swashbuckler Extraordinaire","Sword of Wealth and Power","Tavern Scoundrel","Tempting Contract","The Balrog of Moria","The Belligerent","The Golden City of Orazca","The Matrix of Time","The Reaver Cleaver","The Third Doctor","The Western Cloud","There and Back Again","Thieves' Tools","Tireless Provisioner","Tivit, Seller of Secrets","Treasure Chest","Treasure Dredger","Treasure Map // Treasure Cove","Treasure Vault","Trove of Temptation","Undercity // The Initiative","Undercity Scrounger","Unexpected Windfall","Urabrask // The Great Work","Vault 21: House Gambit","Vault Robber","Vazi, Keen Negotiator","Visions of Ruin","Volatile Fault","Vraska, Relic Seeker","Wanted Scoundrels","Warren Soultrader","Widespread Thieving","Wily Goblin","Xorn","You Find a Cursed Idol","You've Been Caught Stealing","Young Red Dragon // Bathe in Gold","Zhentarim Bandit","Ziatora, the Incinerator"]},"reverseRelated":["Academy Manufactor","An Offer You Can't Refuse","Ancestors' Aid","Ancient Copper Dragon","Atsushi, the Blazing Sky","Axgard Artisan","Baeloth Barrityl, Entertainer","Bank Job","Battle Angels of Tyr","Beamtown Beatstick","Big Score","Big Spender","Bilbo, Retired Burglar","Bill Ferny, Bree Swindler","Black Market Connections","Black Market Tycoon","Blood Money","Bonehoard Dracosaur","Boneyard Desecrator","Bootleggers' Stash","Bottle-Cap Blast","Boxing Ring","Brass's Bounty","Brazen Freebooter","Breeches, Eager Pillager","Bucknard's Everfull Purse","Burakos, Party Leader","Burdened Aerialist","Buy Your Silence","Captain Lannery Storm","Careening Mine Cart","Cavern-Hoard Dragon","Centrifuge","Charming Scoundrel","City of Death","Collector's Vault","Contested Game Ball","Contract Killing","Corsair Captain","Covetous Elegy","Crack Open","Creative Outburst","Culmination of Studies","Currency Converter","Cutthroat Negotiator","Deadeye Plunderers","Deadly Derision","Deadly Dispute","Decadent Dragon // Expensive Taste","Depths of Desire","Descent into Avernus","Diamond Pick-Axe","Dihada, Binder of Wills","Dire Fleet Hoarder","Discerning Financier","Dockside Extortionist","Don Andres, the Renegade","Done for the Day","Dungeon of the Mad Mage","Dungeoneer's Pack","Elemental Masterpiece","Emissary Green","Enterprising Scallywag","Erestor of the Council","Excavation Technique","Exhibition Magician","Exit Through the Grift Shop","Fable of the Mirror-Breaker // Reflection of Kiki-Jiki","Fae Offering","Fain, the Broker","Fake Your Own Death","Flick a Coin","Forging the Tyrite Sword","Forsworn Paladin","Furnace Reins","Gadrak, the Crown-Scourge","Gala Greeters","Galadriel, Gift-Giver","Galazeth Prismari","Ganax, Astral Hunter","Gemcutter Buccaneer","Generous Plunderer","Gilded Pinions","Gimli of the Glittering Caves","Gleaming Barrier","Glittermonger","Gluntch, the Bestower","Glóin, Dwarf Emissary","Goblin Airbrusher","Goblin Shaman","Gold Pan","Gold Rush","Goldspan Dragon","Goldvein Hydra","Goldvein Pick","Gorbag of Minas Morgul","Grabby Giant // That's Mine","Great Train Heist","Greedy Freebooter","Grim Bounty","Grim Hireling","Guild Artisan","Halo Scarab","Heap Gate","Heartless Pillage","Hell to Pay","Henry Wu, InGen Geneticist","Herald of Hadar","Hit the Mother Lode","Hoard Hauler","Hoard Robber","Hoarding Ogre","Hornswoggle","Hullbreacher","Ignacio of Myra's Marvels","Impetuous Lootmonger","Improvised Weaponry","Impulsive Pilferer","Indulge // Excess","Ingenious Mastery","Inspired Tinkering","Instrument of the Bards","Invasion of Ergamon // Truga Cliffcharger","Involuntary Employment","James, Wandering Dad // Follow Him","Jan Jansen, Chaos Crafter","Jared Carthalion","Jewel Thief","Jewel-Eyed Cobra","Jolene, Plundering Pugilist","Jolene, the Plunder Queen","Kalain, Reclusive Painter","Kamachal, Ship's Mascot","Kellogg, Dangerous Mind","Kerblam! Warehouse","Korvold and the Noble Thief","Lara Croft, Tomb Raider","Life Insurance","Lobelia Sackville-Baggins","Loot Dispute","Lost Mine of Phandelver","Lotho, Corrupt Shirriff","Luck Bobblehead","Luxurious Locomotive","Magda, Brazen Outlaw","Magda, the Hoardmaster","Magma Opus","Magmatic Galleon","Mahadi, Emporium Master","Malcolm, Keen-Eyed Navigator","Malik, Grim Manipulator","Marching Duodrone","Mari, the Killing Quill","Marut","Master of Ceremonies","Mastermind Plum","Meet and Greet \"Sisay\"","Megaton's Fate","Mine Raider","Mines of Moria","Misfortune Teller","Monologue Tax","Most Wanted","Mr. House, President and CEO","New New York","Noble's Purse","North Pole Research Base","Nuka-Cola Vending Machine","Oath of the Grey Host","Ognis, the Dragon's Lash","Old Gnawbone","Old Rutstein","Olivia, Opulent Outlaw","Pain Distributor","Patient Naturalist","Patron of the Arts","Pick-a-Beeble","Pinkie Pie","Pirate's Pillage","Pirate's Prize","Pitiless Plunderer","Plundering Barbarian","Plundering Pirate","Poetic Ingenuity","Prismari Command","Prized Statue","Prizefight","Professional Face-Breaker","Prosper, Tome-Bound","Prosperous Innkeeper","Prosperous Partnership","Prosperous Pirates","Prosperous Thief","Prying Blade","RMS Titanic","Racketeer Boss","Ragavan, Nimble Pilferer","Rain of Riches","Ramirez DePietro, Pillager","Rankle and Torbran","Rapacious Dragon","Rashmi and Ragavan","Reckless Endeavor","Reckless Lackey","Reckoner Bankbuster","Redcap Thief","Redrock Sentinel","Revel in Riches","Riveteers Requisitioner","Rose Room Treasurer","Ruthless Knave","Ruthless Technomancer","Safana, Calimport Cutthroat","Sailor of Means","Scion of Opulence","Seize the Spoils","Seize the Spotlight","Shambling Ghast","Shiny Impetus","Skullport Merchant","Smashing Success","Smaug","Smoke Blessing","Smoke Spirits' Aid","Smothering Tithe","Smuggler's Share","Song of Eärendil","Spectrox Mines","Spell Swindle","Spiked Pit Trap","Spiteful Banditry","Spiteful Repossession","Sticky Fingers","Stimulus Package","Storm the Vault // Vault of Catlacan","Storm-Kiln Artist","Strike It Rich","Sudden Breakthrough","Surly Badgersaur","Swarming of Moria","Swashbuckler Extraordinaire","Sword of Wealth and Power","Tavern Scoundrel","Tempting Contract","The Balrog of Moria","The Belligerent","The Golden City of Orazca","The Matrix of Time","The Reaver Cleaver","The Third Doctor","The Western Cloud","There and Back Again","Thieves' Tools","Tireless Provisioner","Tivit, Seller of Secrets","Treasure Chest","Treasure Dredger","Treasure Map // Treasure Cove","Treasure Vault","Trove of Temptation","Undercity // The Initiative","Undercity Scrounger","Unexpected Windfall","Urabrask // The Great Work","Vault 21: House Gambit","Vault Robber","Vazi, Keen Negotiator","Visions of Ruin","Volatile Fault","Vraska, Relic Seeker","Wanted Scoundrels","Warren Soultrader","Widespread Thieving","Wily Goblin","Xorn","You Find a Cursed Idol","You've Been Caught Stealing","Young Red Dragon // Bathe in Gold","Zhentarim Bandit","Ziatora, the Incinerator"],"setCode":"PLNY","subtypes":["Treasure"],"supertypes":[],"text":"{T}, Sacrifice this artifact: Add one mana of any color.","type":"Token Artifact — Treasure","types":["Token","Artifact"],"uuid":"237a0941-3118-512d-a40d-a42c0c518c5a"}],"totalSetSize":0,"translations":{},"type":"promo","meta":{"date":"2024-06-15","version":"5.2.2+20240615"}}
