{"baseSetSize":0,"cards":[{"artist":"Brad Rigney","borderColor":"black","colorIdentity":["B","G"],"colors":["B","G"],"convertedManaCost":0.0,"foreignData":[],"frameVersion":"2015","hasFoil":false,"hasNonFoil":true,"isOversized":true,"isPaper":true,"isStarter":true,"layout":"normal","leadershipSkills":{"brawl":false,"commander":false,"oathbreaker":true},"legalities":{},"loyalty":"20","name":"Garruk the Slayer","number":"1","rarity":"common","rulings":[],"scryfallId":"c18e2175-ec42-47f2-a40f-426ccaa1e89e","scryfallIllustrationId":"a1fac638-d3b4-47ba-9451-617840337a8a","scryfallOracleId":"640c1743-3ad6-46ae-87d1-4d7fbe6a8ff4","subtypes":["Garruk"],"supertypes":["Legendary"],"tcgplayerProductId":91617,"text":"[0]: Put a 2/2 green Wolf creature token onto the battlefield.\n[+4]: Target Wolf creature gets +1/+0 and gains deathtouch until end of turn.\n[−10]: Destroy target creature. Put loyalty counters on Garruk the Slayer equal to that creature's toughness.\n[−25]: Destroy all creatures Garruk the Slayer doesn't control.","type":"Legendary Planeswalker — Garruk","types":["Planeswalker"],"uuid":"c4d600d9-eeb9-5da9-8d44-73c7e44da6b0"}],"code":"PPC1","isFoilOnly":false,"isOnlineOnly":false,"keyruneCode":"M15","meta":{"date":"2020-02-24","version":"4.6.2+20200224"},"name":"M15 Prerelease Challenge","parentCode":"M15","releaseDate":"2014-07-12","tokens":[{"artist":"David Palumbo","borderColor":"black","colorIdentity":["G"],"colors":["G"],"layout":"normal","name":"Wolf","number":"T1","power":"2","reverseRelated":[],"scryfallId":"f36559a1-6fe9-451f-b1a5-5baa9e9301fa","scryfallIllustrationId":"cc035855-ebc1-4443-976c-661e22b89991","scryfallOracleId":"b2224843-8274-4872-a7ca-2adf69cc066b","subtypes":["Wolf"],"supertypes":[],"toughness":"2","type":"Token Creature — Wolf","types":["Token","Creature"],"uuid":"595e7aa2-a2e7-50c4-bfd4-d5654f1ac448"}],"totalSetSize":2,"translations":{},"type":"memorabilia"}
