{"cards":[{"colors":[],"artist":"Alayna Danner","layout":"normal","purchaseUrls":{"tcgplayer":"https://mtgjson.com/links/5678871b275bb4e9","cardKingdomFoil":"https://mtgjson.com/links/d604747b8361caa3"},"identifiers":{"scryfallId":"e0f829da-09a2-4482-8b04-1b63d3a037ee","scryfallOracleId":"bc71ebf6-2056-41f7-be35-b2e5c34afa99","scryfallIllustrationId":"55d7e484-a076-4fc8-b77d-f2edeabc4377","mcmId":"359665","mtgjsonV4Id":"6a962fa1-1edb-5484-aab4-8f266830e382","tcgplayerProductId":"170479","cardKingdomFoilId":"219737","cardsphereId":"56789"},"name":"Plains","language":"English","setCode":"PSS3","borderColor":"black","colorIdentity":["W"],"manaValue":0.0,"convertedManaCost":0.0,"finishes":["foil"],"frameVersion":"2015","hasFoil":true,"hasNonFoil":false,"isPromo":true,"isReprint":true,"number":"1","securityStamp":"oval","promoTypes":["instore"],"rarity":"rare","availability":["paper"],"text":"({T}: Add {W}.)","type":"Basic Land — Plains","legalities":{"standard":"Legal","future":"Legal","historic":"Legal","gladiator":"Legal","pioneer":"Legal","explorer":"Legal","modern":"Legal","legacy":"Legal","pauper":"Legal","vintage":"Legal","penny":"Legal","commander":"Legal","brawl":"Legal","historicbrawl":"Legal","alchemy":"Legal","paupercommander":"Legal","duel":"Legal","premodern":"Legal"},"rulings":[],"supertypes":["Basic"],"types":["Land"],"subtypes":["Plains"],"foreignData":[],"uuid":"06580d91-16d5-54d3-b237-cf96d873f45f","isStarter":true},{"colors":[],"artist":"Alayna Danner","layout":"normal","purchaseUrls":{"tcgplayer":"https://mtgjson.com/links/5b77b50809483632","cardKingdomFoil":"https://mtgjson.com/links/42c3b494a4c6d754"},"identifiers":{"scryfallId":"06e5646b-28f9-4600-89f4-b23a6d7cf7a6","scryfallOracleId":"b2c6aa39-2d2a-459c-a555-fb48ba993373","scryfallIllustrationId":"607e5d2e-f2ad-4170-8061-6f154be3ec25","mcmId":"359664","mtgjsonV4Id":"7b028967-a7e1-5944-a6d1-290221b28342","tcgplayerProductId":"170480","cardKingdomFoilId":"219720","cardsphereId":"56787"},"name":"Island","language":"English","setCode":"PSS3","borderColor":"black","colorIdentity":["U"],"manaValue":0.0,"convertedManaCost":0.0,"finishes":["foil"],"frameVersion":"2015","hasFoil":true,"hasNonFoil":false,"isPromo":true,"isReprint":true,"number":"2","securityStamp":"oval","promoTypes":["instore"],"rarity":"rare","availability":["paper"],"text":"({T}: Add {U}.)","type":"Basic Land — Island","legalities":{"standard":"Legal","future":"Legal","historic":"Legal","gladiator":"Legal","pioneer":"Legal","explorer":"Legal","modern":"Legal","legacy":"Legal","pauper":"Legal","vintage":"Legal","penny":"Legal","commander":"Legal","brawl":"Legal","historicbrawl":"Legal","alchemy":"Legal","paupercommander":"Legal","duel":"Legal","premodern":"Legal"},"rulings":[],"supertypes":["Basic"],"types":["Land"],"subtypes":["Island"],"foreignData":[],"uuid":"dc15cc31-2444-5c56-a2a8-330538472daa","isStarter":true},{"colors":[],"artist":"Alayna Danner","layout":"normal","purchaseUrls":{"tcgplayer":"https://mtgjson.com/links/b6c0c5d1bcea6a86","cardKingdomFoil":"https://mtgjson.com/links/a951d3bb5c952d19"},"identifiers":{"scryfallId":"df5e2dc4-142d-4ee7-8108-b433c4bde53f","scryfallOracleId":"56719f6a-1a6c-4c0a-8d21-18f7d7350b68","scryfallIllustrationId":"af0fa739-df08-426a-bdb9-9936b939cdf7","mcmId":"359663","mtgjsonV4Id":"24e9e242-a972-5c00-81a0-287783a9905f","tcgplayerProductId":"170481","cardKingdomFoilId":"219708","cardsphereId":"56790"},"name":"Swamp","language":"English","setCode":"PSS3","borderColor":"black","colorIdentity":["B"],"manaValue":0.0,"convertedManaCost":0.0,"finishes":["foil"],"frameVersion":"2015","hasFoil":true,"hasNonFoil":false,"isPromo":true,"isReprint":true,"number":"3","securityStamp":"oval","promoTypes":["instore"],"rarity":"rare","availability":["paper"],"text":"({T}: Add {B}.)","type":"Basic Land — Swamp","legalities":{"standard":"Legal","future":"Legal","historic":"Legal","gladiator":"Legal","pioneer":"Legal","explorer":"Legal","modern":"Legal","legacy":"Legal","pauper":"Legal","vintage":"Legal","penny":"Legal","commander":"Legal","brawl":"Legal","historicbrawl":"Legal","alchemy":"Legal","paupercommander":"Legal","duel":"Legal","premodern":"Legal"},"rulings":[],"supertypes":["Basic"],"types":["Land"],"subtypes":["Swamp"],"foreignData":[],"uuid":"bd4c4a0a-0038-5e1e-818a-9922a355175c","isStarter":true},{"colors":[],"artist":"Alayna Danner","layout":"normal","purchaseUrls":{"tcgplayer":"https://mtgjson.com/links/a83068def66d14b7","cardKingdomFoil":"https://mtgjson.com/links/db1bcda0abe072b6"},"identifiers":{"scryfallId":"969054f1-b551-4dee-8fec-f8d8bdc30c35","scryfallOracleId":"a3fb7228-e76b-4e96-a40e-20b5fed75685","scryfallIllustrationId":"bdbfbcb5-44d5-41f2-a846-ac8dcef21e7a","mcmId":"359662","mtgjsonV4Id":"1400ee02-7733-501a-ad87-f6f34d3b3fae","tcgplayerProductId":"170482","cardKingdomFoilId":"219764","cardsphereId":"56788"},"name":"Mountain","language":"English","setCode":"PSS3","borderColor":"black","colorIdentity":["R"],"manaValue":0.0,"convertedManaCost":0.0,"finishes":["foil"],"frameVersion":"2015","hasFoil":true,"hasNonFoil":false,"isPromo":true,"isReprint":true,"number":"4","securityStamp":"oval","promoTypes":["instore"],"rarity":"rare","availability":["paper"],"text":"({T}: Add {R}.)","type":"Basic Land — Mountain","legalities":{"standard":"Legal","future":"Legal","historic":"Legal","gladiator":"Legal","pioneer":"Legal","explorer":"Legal","modern":"Legal","legacy":"Legal","pauper":"Legal","vintage":"Legal","penny":"Legal","commander":"Legal","brawl":"Legal","historicbrawl":"Legal","alchemy":"Legal","paupercommander":"Legal","duel":"Legal","premodern":"Legal"},"rulings":[],"supertypes":["Basic"],"types":["Land"],"subtypes":["Mountain"],"foreignData":[],"uuid":"36f65ad1-774f-54c0-b872-9dc60270eb4d","isStarter":true},{"colors":[],"artist":"Alayna Danner","layout":"normal","purchaseUrls":{"tcgplayer":"https://mtgjson.com/links/4afd53d03efc13f7","cardKingdomFoil":"https://mtgjson.com/links/ac3d2645549bec07"},"identifiers":{"scryfallId":"e832d55c-9f00-4cc0-9593-9604ebc807a4","scryfallOracleId":"b34bb2dc-c1af-4d77-b0b3-a0fb342a5fc6","scryfallIllustrationId":"cb16be03-591b-48ef-92e1-95ceef3bbd0f","mcmId":"359661","mtgjsonV4Id":"d65ac8ef-40de-5f30-a61f-d8cdeee42ff2","tcgplayerProductId":"170478","cardKingdomFoilId":"219683","cardsphereId":"56786"},"name":"Forest","language":"English","setCode":"PSS3","borderColor":"black","colorIdentity":["G"],"manaValue":0.0,"convertedManaCost":0.0,"finishes":["foil"],"frameVersion":"2015","hasFoil":true,"hasNonFoil":false,"isPromo":true,"isReprint":true,"number":"5","securityStamp":"oval","promoTypes":["instore"],"rarity":"rare","availability":["paper"],"text":"({T}: Add {G}.)","type":"Basic Land — Forest","legalities":{"standard":"Legal","future":"Legal","historic":"Legal","gladiator":"Legal","pioneer":"Legal","explorer":"Legal","modern":"Legal","legacy":"Legal","pauper":"Legal","vintage":"Legal","penny":"Legal","commander":"Legal","brawl":"Legal","historicbrawl":"Legal","alchemy":"Legal","paupercommander":"Legal","duel":"Legal","premodern":"Legal"},"rulings":[],"supertypes":["Basic"],"types":["Land"],"subtypes":["Forest"],"foreignData":[],"uuid":"e72d1080-cf7f-538c-b21f-3fcd909d4190","isStarter":true}],"tokens":[],"name":"M19 Standard Showdown","code":"PSS3","type":"promo","keyruneCode":"PMEI","releaseDate":"2018-07-13","parentCode":"M19","isOnlineOnly":false,"isFoilOnly":true,"translations":{},"baseSetSize":5,"totalSetSize":5,"meta":{"date":"2022-06-08","version":"5.2.0+20220608"}}
